Metadata-Version: 1.2
Name: kec-training
Version: 0.3.0
Summary: A package to to assist in KEC Training
Home-page: UNKNOWN
Author: Nishan Khanal
Author-email: nishan.khanal98@gmail.com
License: UNKNOWN
Platform: UNKNOWN
Classifier: Programming Language :: Python :: 3
Classifier: License :: OSI Approved :: MIT License
Classifier: Operating System :: OS Independent
Requires-Python: >=3.6
